mac_to_ip/__init__.py
mac_to_ip/mac_to_ip.py
mac_to_ip-0.1.0.dist-info/AUTHORS.rst
mac_to_ip-0.1.0.dist-info/LICENSE
mac_to_ip-0.1.0.dist-info/METADATA
mac_to_ip-0.1.0.dist-info/WHEEL
mac_to_ip-0.1.0.dist-info/top_level.txt
mac_to_ip-0.1.0.dist-info/RECORD
