Metadata-Version: 2.1
Name: mac-to-ip
Version: 0.1.0
Summary: Find ip addresses with known MAC addresses
Home-page: https://github.com/cartovarc/mac_to_ip
Author: Carlos Tovar
Author-email: cartovarc@gmail.com
License: MIT license
Keywords: mac_to_ip
Platform: UNKNOWN
Classifier: Development Status :: 2 - Pre-Alpha
Classifier: Intended Audience :: Developers
Classifier: License :: OSI Approved :: MIT License
Classifier: Natural Language :: English
Classifier: Programming Language :: Python :: 3.6
Requires-Python: >=3.6
